hzzzwl_agriculture_mcp/__init__.py
hzzzwl_agriculture_mcp/server.py
hzzzwl_agriculture_mcp-0.1.7.dist-info/METADATA
hzzzwl_agriculture_mcp-0.1.7.dist-info/WHEEL
hzzzwl_agriculture_mcp-0.1.7.dist-info/entry_points.txt
hzzzwl_agriculture_mcp-0.1.7.dist-info/RECORD
