Metadata-Version: 2.4
Name: hzzzwl-agriculture-mcp
Version: 0.1.7
Summary: A tool for search agriculture information
Author-email: hzzzwl <1085501772@qq.com>
License-Expression: MIT
Classifier: Programming Language :: Python :: 3
Requires-Python: >=3.12
Requires-Dist: httpx>=0.28.1
Requires-Dist: mcp[cli]>=1.9.0
